StadisticsML/Funciones.py
StadisticsML/__init__.py
StadisticsML-1.0.0.dist-info/METADATA
StadisticsML-1.0.0.dist-info/WHEEL
StadisticsML-1.0.0.dist-info/top_level.txt
StadisticsML-1.0.0.dist-info/RECORD
