Metadata-Version: 2.1
Name: StadisticsML
Version: 1.0.0
Summary: Librería para obtener valores estadísticos para pruebas de distribución de signos, determinación de outliers y pruebas Durbin-Watson
Home-page: https://github.com/Guacen/StadisticsML.git
Author: Jorge Eduardo Londoño Arango
Author-email: joelondonoar@unal.edu.co
License: MIT
Requires-Dist: numpy
Requires-Dist: scipy
Requires-Dist: scikit-learn
Requires-Dist: tensorflow
Requires-Dist: keras
Requires-Dist: matplotlib
Requires-Dist: pandas
Requires-Dist: scikeras
